{"title":"United Kingdom","instanceSlug":"uk","tags":[],"parents":[],"artists":[{"title":"After the Fire","instanceSlug":"after-the-fire","tags":[],"parents":[],"genres":[],"type":"g","origin":"uk","birth":"","death":"","complete":false},{"title":"Annie Lennox","instanceSlug":"annie-lennox","tags":[],"parents":[],"genres":["pop"],"members":[],"origin":"uk","birth":"","death":"","complete":true,"type":"f"},{"title":"The Cardigans","instanceSlug":"cardigans","tags":[],"parents":[],"genres":[],"members":[],"xref":[],"complete":false,"origin":"uk","birth":"","death":"","type":"g"},{"title":"Cathy Dennis","instanceSlug":"cathy-dennis","tags":["1990s"],"parents":[],"genres":[],"members":[],"complete":false,"origin":"uk","birth":"","death":"","type":"f"},{"title":"The Clash","instanceSlug":"clash","tags":[],"parents":[],"genres":[],"members":[],"xref":[],"complete":false,"origin":"uk","birth":"","death":"","type":"g"},{"title":"Ed Sheeran","instanceSlug":"ed-sheeran","tags":[],"parents":[],"genres":[],"members":[],"complete":false,"origin":"uk","birth":"","death":""},{"title":"Elton John","instanceSlug":"elton-john","tags":["1970s","1980s","1990s"],"parents":[],"genres":["pop"],"members":[],"complete":true,"origin":"uk","birth":"","death":"","type":"m"},{"title":"Erasure","instanceSlug":"erasure","tags":[],"parents":[],"genres":[],"members":[],"complete":false,"origin":"uk","birth":"","death":"","type":"g"},{"title":"Eric Clapton","instanceSlug":"eric-clapton","tags":["1970s","1980s","1990s"],"parents":[],"genres":["rock","blues","blues-rock"],"complete":false,"origin":"uk","birth":"","death":"","type":"m"},{"title":"George Harrison","instanceSlug":"george-harrison","tags":["1970s","1980s"],"parents":[],"genres":[],"members":[],"complete":false,"origin":"uk","birth":"","death":"","type":"m"},{"title":"George Michael","instanceSlug":"george-michael","tags":["1980s","1990s"],"parents":[],"genres":[],"members":[],"complete":false,"origin":"uk","birth":"","death":"","type":"m"},{"title":"Howard Jones","instanceSlug":"howard-jones","tags":[],"parents":[],"genres":["pop"],"members":[],"complete":true,"origin":"uk","birth":"","death":"","type":"m"},{"title":"Julian Lennon","instanceSlug":"julian-lennon","xref":["john-lennon"],"parents":[],"genres":["pop"],"members":[],"complete":false,"origin":"uk","birth":"","death":"","type":"m"},{"title":"Leo Sayre","instanceSlug":"leo-sayre","tags":[],"parents":[],"genres":["pop"],"members":[],"xref":[],"complete":false,"origin":"uk","birth":"","death":"","type":"m"},{"title":"Level 42","instanceSlug":"level-42","tags":[],"parents":[],"genres":[],"members":[],"xref":[],"complete":false,"origin":"uk","birth":"","death":"","type":"g"},{"title":"M-People","instanceSlug":"m-people","tags":[],"parents":[],"genres":[],"members":[],"xref":[],"complete":false,"origin":"uk","birth":"","death":"","type":"g"},{"title":"Mick Jagger","instanceSlug":"mick-jagger","tags":[],"parents":[],"genres":["rock"],"members":[],"xref":["rolling-stones"],"complete":false,"origin":"uk","birth":"","death":"","type":"m"},{"title":"Mike & the Mechanics","instanceSlug":"mike-mechanics","tags":[],"parents":[],"genres":[],"members":["paul-carrack"],"xref":[],"complete":false,"origin":"uk","birth":"","death":"","type":"g"},{"title":"Moody Blues","instanceSlug":"moody-blues","tags":["1970s","1980s"],"parents":[],"genres":[],"members":[],"xref":[],"complete":false,"origin":"uk","birth":"","death":"","type":"g"},{"title":"Naked Eyes","instanceSlug":"naked-eyes","tags":[],"parents":[],"genres":[],"members":[],"xref":[],"complete":false,"origin":"uk","birth":"","death":"","type":"g"},{"title":"Nicki French","instanceSlug":"nikki-french","tags":[],"parents":[],"genres":["dance"],"members":[],"xref":[],"complete":false,"origin":"uk","birth":"","death":"","type":"f"},{"title":["One Direction",true],"instanceSlug":"one-direction","tags":[],"parents":[],"genres":["2010s"],"members":[],"xref":[],"complete":false,"origin":"uk","birth":"","death":"","type":"g"},{"title":"Pet Shop Boys","instanceSlug":"pet-shop-boys","tags":[],"parents":[],"genres":[],"members":[],"xref":[],"complete":false,"origin":"uk","birth":"","death":"","type":"g"},{"title":"Pete Townsend","instanceSlug":"pete-townsend","tags":[],"parents":[],"genres":[],"members":[],"xref":[],"complete":false,"origin":"uk","birth":"","death":"","type":"m"},{"title":"Peter Frampton","instanceSlug":"peter-frampton","tags":[],"parents":[],"genres":[],"members":[],"xref":[],"complete":false,"origin":"uk","birth":"","death":"","type":"m"},{"title":"Peter Gabriel","instanceSlug":"peter-gabriel","tags":[],"parents":[],"genres":[],"members":[],"xref":[],"complete":false,"origin":"uk","birth":"","death":"","type":"m"},{"title":"Rick Astley","instanceSlug":"rick-astley","tags":[],"parents":[],"genres":["pop"],"members":[],"xref":[],"complete":true,"origin":"uk","birth":"","death":"","type":"m"},{"title":"Spice Girls","instanceSlug":"spice-girls","tags":["all-female"],"parents":[],"genres":[],"members":[],"xref":[],"complete":false,"origin":"uk","birth":"","death":"","type":"g"},{"title":"Sweet","instanceSlug":"sweet","tags":[],"parents":[],"genres":[],"members":[],"xref":[],"complete":false,"origin":"uk","birth":"","death":"","type":"g"},{"title":"Swing Out Sister","instanceSlug":"swing-out-sister","tags":[],"parents":[],"genres":[],"members":[],"xref":[],"complete":false,"origin":"uk","birth":"","death":"","type":"g"},{"title":"UB40","instanceSlug":"ub40","tags":[],"parents":[],"genres":[],"members":[],"xref":[],"complete":false,"origin":"uk","birth":"","death":"","type":"g"},{"title":"The Who","instanceSlug":"who","tags":["1960s","1970s"],"parents":[],"genres":["rock"],"members":["roger-daltry","pete-townsend"],"xref":[],"complete":true,"origin":"uk","birth":"","death":"","type":"g"}]}