{"title":"It's So Hard to Say Goodbye to Yesterday","instanceSlug":1075,"tags":["#1","#1-r&b"],"parents":[],"genre":"soul","debut":"1991-10","playlists":[],"ranks":[15,8.5,4,3.1,2.5,2.4,2.69,2.98,3.56,4.43,5.59,7.04,8.78,10.81,13.13,15.74,18.64,21.83,25.31,29.08,33.14,37.49,42.13,47.06,52.28,57.79,63.59,69.68],"artists":[{"slug":"boyz-ii-men","title":"Boyz II Men","roleSlug":true}],"debutRank":15,"peakRank":2.4,"duration":7,"score":20.52,"genres":[{"slug":"soul","title":"Soul"}],"source":null,"rank":299}