{"title":"Crazy for You","instanceSlug":117,"tags":["#1","for-you"],"playlists":[{"title":"Ballads","instanceSlug":"ballad","tags":[],"parents":[]},{"title":"Songs from Movies","instanceSlug":"movie","tags":[],"columns":["rank","title","artist","source","score","debutDate"]}],"genre":"pop","debut":"1985-04","source":{"title":"Vision Quest","instanceSlug":"vision-quest","tags":[],"parents":[],"type":"movie"},"ranks":{"artist:jellybean":{"rank":10,"total":12},"artist:madonna":{"rank":31,"total":45},"genre:pop":{"rank":587,"total":1403},"playlist:movie":{"rank":63,"total":143},"playlist:ballad":{"rank":65,"total":134},"source:vision-quest":{"rank":1,"total":2},"decade:1980s":{"rank":573,"total":1542},"year:1985":{"rank":40,"total":167}},"artists":[{"slug":"madonna","title":"Madonna","roleSlug":true},{"slug":"jellybean","title":"John Benitez (Jellybean)","roleSlug":"producer"}],"scores":[0.126,0.353,0.505,0.567,0.573,0.556,0.551,0.541,0.526,0.506,0.481,0.451,0.416,0.376,0.331,0.281,0.226,0.166,0.101,0.031,0],"score":7.664000000000001,"debutScore":0.126,"peakScore":0.573,"duration":6,"genres":[{"instanceSlug":"pop","title":"Pop","parents":[]}],"debutEra":{"slug":"1985-04","title":"April 1985","type":"month","decade":1980,"year":1985,"month":4},"rank":1249}