{"title":"Rock With You","instanceSlug":1214,"tags":["#1","#1-adult-contemporary","#1-hot-100"],"source":{"title":"Off the Wall","instanceSlug":"off-the-wall","tags":[],"type":"album"},"genres":[{"instanceSlug":"disco","title":"Disco","parents":["dance"]},{"instanceSlug":"urban","title":"Urban / R&B","parents":[]},{"instanceSlug":"soul","title":"Soul","parents":["urban"]}],"debut":"1979-12","playlists":[],"artists":[{"slug":"michael-jackson","title":"Michael Jackson","roleSlug":true},{"slug":"rod-temperton"},{"slug":"quincy-jones","title":"Quincy Jones","roleSlug":"producer"}],"scores":[0.075,0.232,0.463,0.582,0.694,0.681,0.656,0.633,0.612,0.582,0.546,0.541,0.531,0.516,0.496,0.471,0.441,0.406,0.366,0.321,0.271,0.216,0.156,0.091,0.021,0],"ranks":{"artist:michael-jackson":{"rank":19,"total":69},"artist:quincy-jones":{"rank":15,"total":30},"artist:rod-temperton":{"rank":3,"total":3},"genre:urban":{"rank":23,"total":132},"genre:soul":{"rank":50,"total":227},"genre:disco":{"rank":6,"total":41},"source:off-the-wall":{"rank":2,"total":4},"decade:1970s":{"rank":44,"total":512},"year:1979":{"rank":10,"total":84}},"score":10.600000000000001,"debutScore":0.075,"peakScore":0.694,"duration":7,"debutEra":{"slug":"1979-12","title":"December 1979","type":"month","decade":1970,"year":1979,"month":12},"rank":494}