{"title":"Wrap Her Up","instanceSlug":1381,"tags":["her","up","wrap"],"parents":[],"genre":"pop","debut":"1985-11","playlists":[],"ranks":{"artist:elton-john":30,"artist:george-michael":6,"genre:pop":1303,"decade:1980s":1029,"year:1985":139},"artists":[{"slug":"elton-john","title":"Elton John","roleSlug":true},{"slug":"george-michael","title":"George Michael","roleSlug":"backup"}],"scores":null,"genres":[{"slug":"pop","title":"Pop"}],"source":null,"debutEra":{"slug":"1985-11","title":"November 1985","decade":1980,"year":1985,"month":11},"rank":422}