{"title":"Leave a Light On for Me","instanceSlug":1415,"tags":["leave","light"],"parents":[],"genre":"pop","debut":"1989-10","playlists":[],"ranks":{"artist:belinda-carlisle":{"rank":3,"total":4},"genre:pop":{"rank":1017,"total":1340},"decade:1980s":{"rank":1023,"total":1495},"year:1989":{"rank":124,"total":149}},"artists":[{"slug":"belinda-carlisle","title":"Belinda Carlisle","roleSlug":true}],"scores":null,"score":null,"genres":[{"slug":"pop"}],"source":null,"debutEra":{"slug":"1989-10","title":"October 1989","decade":1980,"year":1989,"month":10},"rank":2551}