{"title":"The Sweetest Thing (I've Ever Known)","instanceSlug":1535,"tags":["#1","#1-adult-contemporary","#1-country","sweetest-thing"],"parents":[],"genre":"country","debut":"1981-11","playlists":[],"ranks":{"artist:juice-newton":{"rank":4,"total":5},"genre:country":{"rank":57,"total":80},"decade:1980s":{"rank":1373,"total":1483},"year:1981":{"rank":100,"total":117}},"artists":[{"slug":"juice-newton","title":"Juice Newton","roleSlug":true}],"scores":null,"score":null,"genres":[{"slug":"country","title":"Country"}],"source":null,"debutEra":{"slug":"1981-11","title":"November 1981","decade":1980,"year":1981,"month":11},"rank":2381}