{"title":"Can't Stop","instanceSlug":156,"tags":["can't-stop"],"parents":[],"genre":"soul","debut":"1990-09","ranks":{"artist:after-7":1,"genre:soul":39,"decade:1990s":126,"year:1990":20},"artists":[{"slug":"after-7","title":"After 7","roleSlug":true}],"scores":[0.171,0.381,0.592,0.804,0.787,0.681,0.676,0.666,0.651,0.631,0.606,0.576,0.541,0.501,0.456,0.406,0.351,0.291,0.226,0.156,0.081,0.001,0],"debutScore":0.171,"peakScore":0.804,"duration":6,"score":10.232000000000001,"genres":[{"slug":"soul","title":"Soul"}],"playlists":[],"source":null,"debutEra":{"slug":"1990-09","title":"September 1990","decade":1990,"year":1990,"month":9},"rank":346}