{"title":"Forever My Lady","instanceSlug":1560,"tags":["forever","lady","my"],"parents":[],"genre":"soul","debut":"1991-12","playlists":[],"ranks":{"artist:jodeci":{"rank":1,"total":2},"genre:soul":{"rank":140,"total":223},"decade:1990s":{"rank":795,"total":869},"year:1991":{"rank":105,"total":143}},"artists":[{"slug":"jodeci","title":"Jodeci","roleSlug":true}],"scores":null,"score":null,"genres":[{"instanceSlug":"soul","title":"Soul","parents":["urban"]}],"source":{},"debutEra":{"slug":"1991-12","title":"December 1991","decade":1990,"year":1991,"month":12},"rank":2399}