{
  "title": "Holding On",
  "instanceSlug": 1576,
  "tags": [
    "hold",
    "holding",
    "hold-on",
    "on"
  ],
  "parents": [
  ],
  "genre": "pop",
  "debut": "1988-12",
  "playlists": [
  ],
  "ranks": [
    15,
    8,
    5.5,
    3.7,
    3,
    3.1,
    3.25,
    3.7
  ],
  "artists": [
    {
      "slug": "steve-winwood",
      "title": "Steve Winwood",
      "roleSlug": true
    }
  ],
  "scores": [
    0.097,
    0.306,
    0.431,
    0.563,
    0.633,
    0.622,
    0.607,
    0.563,
    0.558,
    0.548,
    0.533,
    0.513,
    0.488,
    0.458,
    0.423,
    0.383,
    0.338,
    0.288,
    0.233,
    0.173,
    0.108,
    0.038,
    0
  ],
  "debutScore": 0.097,
  "peakScore": 0.097,
  "duration": 5.75,
  "score": 8.904000000000002,
  "genres": [
    {
      "slug": "pop",
      "title": "Pop"
    }
  ],
  "source": null,
  "rank": 486
}