{
  "title": "The Power of Love",
  "instanceSlug": 1722,
  "tags": [
  ],
  "parents": [
  ],
  "genre": "adult-contemporary",
  "debut": "1994-01",
  "playlists": [
    {
      "slug": "remake",
      "title": "Remakes"
    }
  ],
  "ranks": [
    22,
    17,
    15,
    13,
    14.6
  ],
  "artists": [
    {
      "slug": "celine-dion",
      "title": "Celine Dion",
      "roleSlug": true
    }
  ],
  "scores": [
    0.055,
    0.097,
    0.145,
    0.106,
    0.101,
    0.091,
    0.076,
    0.056,
    0.031,
    0.001,
    0
  ],
  "debutScore": 0.055,
  "peakScore": 0.055,
  "duration": 2.75,
  "score": 0.759,
  "genres": [
    {
      "slug": "adult-contemporary",
      "title": "Adult Contemporary"
    }
  ],
  "source": null,
  "rank": 1535
}