{"title":"Get Lucky","instanceSlug":1788,"tags":["#1","#1-rdwt40-hot-adult"],"parents":[],"genre":"pop","debut":2013,"playlists":[],"ranks":{"artist:pharrell-williams":{"rank":3,"total":3},"artist:daft-punk":{"rank":1,"total":1},"artist:nile-rodgers":{"rank":1,"total":1},"genre:pop":{"rank":485,"total":1407},"decade:2010s":{"rank":35,"total":107},"year:2013":{"rank":6,"total":12}},"artists":[{"slug":"daft-punk","title":"Daft Punk","roleSlug":true},{"slug":"pharrell-williams","title":"Pharrell Williams","roleSlug":"feature"},{"slug":"nile-rodgers","title":"Nile Rodgers","roleSlug":"backup"}],"scores":[0.065,0.351,0.537,0.582,0.612,0.592,0.587,0.577,0.562,0.542,0.517,0.487,0.452,0.412,0.367,0.317,0.262,0.202,0.137,0.067,0],"score":8.227000000000002,"debutScore":0.065,"peakScore":0.612,"duration":6,"genres":[{"instanceSlug":"pop","title":"Pop","parents":[]}],"source":{},"debutEra":{"slug":2013,"title":2013,"type":"year","decade":2010,"year":2013},"rank":1051}