{"title":"Tenderness","instanceSlug":1953,"tags":[],"parents":[],"genre":"pop","debut":"1985-02","playlists":[],"ranks":{"artist:general-public":{"rank":1,"total":2},"genre:pop":{"rank":400,"total":1382},"decade:1980s":{"rank":427,"total":1496},"year:1985":{"rank":33,"total":164}},"artists":[{"slug":"general-public","title":"General Public","roleSlug":true}],"scores":[0.075,0.216,0.361,0.408,0.45,0.498,0.513,0.517,0.498,0.402,0.397,0.387,0.372,0.352,0.327,0.297,0.262,0.222,0.177,0.127,0.072,0.012,0],"score":6.941999999999998,"debutScore":0.075,"peakScore":0.517,"duration":6,"genres":[{"instanceSlug":"pop","title":"Pop","parents":[]}],"source":{},"debutEra":{"slug":"1985-02","title":"February 1985","type":"month","decade":1980,"year":1985,"month":2},"rank":809}