{"title":"Along Comes a Woman","instanceSlug":2000,"tags":[],"genres":[{"instanceSlug":"jazz-rock","title":"Jazz Rock","parents":["rock"]},{"instanceSlug":"pop","title":"Pop","parents":[]}],"source":{"title":"Chicago 17","instanceSlug":"chicago17","tags":["chicago"],"type":"album"},"debut":"1985-03","playlists":[],"ranks":{"artist:chicago":{"rank":16,"total":23},"artist:david-foster":{"rank":5,"total":5},"genre:pop":{"rank":876,"total":1382},"genre:jazz-rock":{"rank":9,"total":11},"source:chicago17":{"rank":4,"total":4},"decade:1980s":{"rank":1421,"total":1496},"year:1985":{"rank":126,"total":164}},"artists":[{"slug":"chicago","title":"Chicago","roleSlug":true},{"slug":"david-foster","title":"David Foster","roleSlug":"producer"}],"scores":null,"score":null,"debutEra":{"slug":"1985-03","title":"March 1985","type":"month","decade":1980,"year":1985,"month":3},"rank":2394}