{"title":"After Midnight","instanceSlug":2006,"tags":[],"parents":[],"genre":"blues","debut":1970,"playlists":[],"ranks":{"artist:eric-clapton":{"rank":3,"total":17},"genre:blues":{"rank":2,"total":11},"decade:1970s":{"rank":108,"total":509},"year:1970":{"rank":4,"total":23}},"artists":[{"slug":"eric-clapton","title":"Eric Clapton","roleSlug":true}],"scores":[0.097,0.768,0.708,0.703,0.693,0.678,0.658,0.633,0.603,0.568,0.528,0.483,0.433,0.378,0.318,0.253,0.183,0.108,0.028,0],"score":8.821,"debutScore":0.097,"peakScore":0.768,"duration":5,"genres":[{"instanceSlug":"blues","title":"Blues","parents":[]}],"source":{},"debutEra":{"slug":1970,"title":1970,"type":"year","decade":1970,"year":1970},"rank":855}