{"title":"Head to Toe","instanceSlug":2042,"tags":[],"parents":[],"genre":"dance","debut":"1987-05","playlists":[],"ranks":{"artist:lisa-lisa-cult-jam":2,"genre:dance":54,"decade:1980s":322,"year:1987":59},"artists":[{"slug":"lisa-lisa-cult-jam","title":"Lisa Lisa & Cult Jam","roleSlug":true}],"scores":[0.12,0.306,0.498,0.582,0.633,0.592,0.546,0.541,0.531,0.516,0.496,0.471,0.441,0.406,0.366,0.321,0.271,0.216,0.156,0.091,0.021,0],"debutScore":0.12,"peakScore":0.633,"duration":6,"score":8.121,"genres":[{"slug":"dance","title":"Dance"}],"source":null,"debutEra":{"slug":"1987-05","title":"May 1987","decade":1980,"year":1987,"month":5},"rank":1151}