{"title":"Can't Get It Out of My Head","instanceSlug":2271,"tags":[],"parents":[],"genre":"orchestral-rock","debut":1975,"playlists":[],"ranks":{"artist:electric-light-orchestra":{"rank":5,"total":11},"genre:orchestral-rock":{"rank":2,"total":9},"decade:1970s":{"rank":246,"total":515},"year:1975":{"rank":26,"total":46}},"artists":[{"slug":"electric-light-orchestra","title":"Electric Light Orchestra","roleSlug":true}],"scores":[0.09525,0.26225,0.4125,0.46625,0.471,0.49,0.46175,0.4505,0.43425,0.413,0.38675000000000004,0.35550000000000004,0.31925000000000003,0.278,0.23175,0.18674999999999997,0.14675000000000002,0.11750000000000001,0.08750000000000001,0.06675,0.04925,0.0305,0.0105,0],"score":6.2235000000000005,"debutScore":0.09525,"peakScore":0.49,"duration":6,"genres":[{"instanceSlug":"orchestral-rock","title":"Orchestral Rock","parents":["rock"]}],"source":{},"debutEra":{"slug":1975,"title":1975,"type":"year","decade":1970,"year":1975},"rank":1687}