{"title":"Somebody to Love","instanceSlug":2435,"tags":[],"parents":[],"genre":"pop","debut":"1993-06","playlists":[],"ranks":{"artist:george-michael":{"rank":11,"total":13},"artist:queen":{"rank":14,"total":14},"genre:pop":{"rank":1284,"total":1338},"decade:1990s":{"rank":519,"total":864},"year:1993":{"rank":93,"total":107}},"artists":[{"slug":"george-michael","title":"George Michael","roleSlug":true},{"slug":"queen","title":"Queen","roleSlug":true}],"scores":null,"score":null,"genres":[{"slug":"pop","title":"Pop"}],"source":null,"debutEra":{"slug":"1993-06","title":"June 1993","decade":1990,"year":1993,"month":6},"rank":2967}