{"title":"Even Now","instanceSlug":2609,"tags":[],"parents":[],"genre":"rock","debut":"1983-04","playlists":[],"ranks":{"artist:bob-seger":{"rank":12,"total":15},"genre:rock":{"rank":353,"total":618},"decade:1980s":{"rank":1358,"total":1483},"year:1983":{"rank":119,"total":149}},"artists":[{"slug":"bob-seger","title":"Bob Seger","roleSlug":true}],"scores":null,"score":null,"genres":[{"slug":"rock","title":"Rock"}],"source":null,"debutEra":{"slug":"1983-04","title":"April 1983","decade":1980,"year":1983,"month":4},"rank":1771}