{"title":"Breaking Away","instanceSlug":2837,"tags":[],"parents":[],"genre":"pop","debut":"1981-09","playlists":[],"ranks":{"artist:balance":{"rank":1,"total":1},"genre:pop":{"rank":1341,"total":1405},"decade:1980s":{"rank":1457,"total":1538},"year:1981":{"rank":116,"total":120}},"artists":[{"slug":"balance","title":"Balance","roleSlug":true}],"scores":null,"score":null,"genres":[{"instanceSlug":"pop","title":"Pop","parents":[]}],"source":{},"debutEra":{"slug":"1981-09","title":"September 1981","type":"month","decade":1980,"year":1981,"month":9},"rank":3030}