{"title":"Bye Bye Bye","instanceSlug":2983,"tags":[],"genre":"pop","debut":"2000-02","playlists":[],"artists":[{"slug":"nsync","title":"*NSYNC","roleSlug":true},{"slug":"justin-timberlake","title":"Justin Timberlake","roleSlug":"member"}],"scores":[0.25,0.68,0.81,0.82,0.81,0.8,0.75,0.745,0.735,0.72,0.7,0.675,0.645,0.61,0.57,0.525,0.475,0.42,0.36,0.295,0.225,0.15,0.07,0],"ranks":{"artist:nsync":{"rank":1,"total":8},"artist:justin-timberlake":{"rank":7,"total":14},"genre:pop":{"rank":118,"total":1405},"decade:2000s":{"rank":11,"total":122},"year:2000":{"rank":3,"total":23}},"score":12.84,"debutScore":0.25,"peakScore":0.82,"duration":6,"genres":[{"instanceSlug":"pop","title":"Pop","parents":[]}],"source":{},"debutEra":{"slug":"2000-02","title":"February 2000","type":"month","decade":2000,"year":2000,"month":2},"rank":236}