{"title":"Tell Her No","instanceSlug":356,"tags":["tell-her"],"playlists":[{"slug":"remake"},{"slug":"summer"}],"parents":[],"genre":"pop","debut":"1983-09","ranks":{"artist:juice-newton":{"rank":5,"total":5},"genre:pop":{"rank":1029,"total":1340},"playlist:summer":{"rank":192,"total":210},"playlist:remake":{"rank":38,"total":47},"decade:1980s":{"rank":979,"total":1495},"year:1983":{"rank":147,"total":149}},"artists":[{"slug":"juice-newton","title":"Juice Newton","roleSlug":true}],"scores":null,"score":null,"genres":[{"slug":"pop"}],"source":null,"debutEra":{"slug":"1983-09","title":"September 1983","decade":1980,"year":1983,"month":9},"rank":2347}