{"title":"Where Do You Go","instanceSlug":601,"tags":[],"parents":[],"genre":"dance","debut":"1996-08","playlists":[{"slug":"summer"}],"ranks":{"artist:no-mercy":{"rank":2,"total":2},"genre:dance":{"rank":82,"total":123},"playlist:summer":{"rank":151,"total":210},"decade:1990s":{"rank":398,"total":869},"year:1996":{"rank":33,"total":62}},"artists":[{"slug":"no-mercy","title":"No Mercy","roleSlug":true}],"scores":[0.015,0.177,0.286,0.319,0.337,0.33,0.314,0.286,0.246,0.241,0.231,0.216,0.196,0.171,0.141,0.106,0.066,0.021,0],"score":3.699,"debutScore":0.015,"peakScore":0.337,"duration":5,"genres":[{"slug":"dance"}],"source":null,"debutEra":{"slug":"1996-08","title":"August 1996","decade":1990,"year":1996,"month":8},"rank":1279}