{"title":"Unwell","instanceSlug":62,"tags":["un","well"],"parents":[],"genre":"rock","debut":2002,"ranks":{"artist:rob-thomas":{"rank":3,"total":3},"genre:rock":{"rank":513,"total":630},"decade:2000s":{"rank":111,"total":119},"year:2002":{"rank":9,"total":11}},"artists":[{"slug":"rob-thomas","title":"Rob Thomas","roleSlug":true}],"scores":null,"score":null,"genres":[{"instanceSlug":"rock","title":"Rock","parents":[]}],"playlists":[],"source":{},"debutEra":{"slug":2002,"title":2002,"decade":2000,"year":2002},"rank":2640}