{"title":"Lady (You Bring Me Up)","instanceSlug":904,"tags":[],"parents":[],"genre":"soul","debut":"1981-10","playlists":[],"ranks":{"artist:commodores":1,"genre:soul":7,"decade:1980s":55,"year:1981":3},"artists":[{"slug":"commodores","title":"Commodores","roleSlug":true}],"scores":[0.12,0.463,0.768,0.939,0.912,0.859,0.854,0.844,0.829,0.809,0.784,0.754,0.719,0.679,0.634,0.584,0.529,0.469,0.404,0.334,0.259,0.179,0.094,0.004,0],"debutScore":0.12,"peakScore":0.939,"duration":7,"score":13.822999999999999,"genres":[{"slug":"soul","title":"Soul"}],"source":null,"debutEra":{"slug":"1981-10","title":"October 1981","decade":1980,"year":1981,"month":10},"rank":100}