{"title":"Hill Street Blues Theme","instanceSlug":914,"tags":[],"genre":"pop","debut":"1981-10","source":{"title":"Hill Street Blues","instanceSlug":"hill-street-blues","tags":[],"parents":[],"type":"tv"},"playlists":[{"slug":"instrumental","title":"Instrumentals"},{"slug":"tv-theme","title":"TV Show Themes"}],"ranks":[18,10,7.5,5.8,5,5.7,5.84,6.12,6.54,7.1,7.8,8.64,9.62,10.74,12,13.4,14.94,16.62,18.44,20.4,22.5,24.74,27.12,29.64,32.3,35.1,38.04,41.12,44.34,47.7,51.2,54.84],"artists":[{"slug":"mike-post","title":"Mike Post","roleSlug":true}],"debutRank":18,"peakRank":5,"duration":8,"score":14.91,"genres":[{"slug":"pop","title":"Pop"}],"rank":942}