{"title":"Arthur's Theme (Best That You Can Do)","instanceSlug":923,"tags":["#1","#1-adult-contemporary","#1-hot-100"],"genre":"adult-contemporary","debut":"1981-09","source":{"instanceSlug":"arthur","title":"Arthur","tags":[],"parents":[],"type":"movie"},"playlists":[],"artists":[{"slug":"christopher-cross","title":"Christopher Cross","roleSlug":true},{"slug":"carol-bayer-sager"}],"scores":[0.321,0.645,0.662,0.668,0.672,0.667,0.657,0.642,0.622,0.597,0.567,0.532,0.492,0.447,0.397,0.342,0.282,0.217,0.147,0.072,0],"ranks":{"artist:carol-bayer-sager":{"rank":4,"total":12},"artist:christopher-cross":{"rank":2,"total":6},"genre:adult-contemporary":{"rank":24,"total":156},"source:arthur":{"rank":1,"total":1},"decade:1980s":{"rank":332,"total":1531},"year:1981":{"rank":41,"total":120}},"score":9.648000000000001,"debutScore":0.321,"peakScore":0.672,"duration":6,"genres":[{"instanceSlug":"adult-contemporary","title":"Adult Contemporary","parents":[]}],"debutEra":{"slug":"1981-09","title":"September 1981","type":"month","decade":1980,"year":1981,"month":9},"rank":681}