{"title":"Let's Wait Awhile","instanceSlug":95,"tags":["#1","#1-r&b"],"parents":[],"genre":"pop","debut":"1987-02","artists":[{"slug":"janet-jackson","title":"Janet Jackson","roleSlug":true}],"scores":[0.17,0.452,0.652,0.744,0.787,0.772,0.767,0.757,0.742,0.722,0.697,0.667,0.632,0.592,0.547,0.497,0.442,0.382,0.317,0.247,0.172,0.092,0.007,0],"ranks":{"artist:janet-jackson":{"rank":6,"total":28},"genre:pop":{"rank":170,"total":1404},"decade:1980s":{"rank":172,"total":1537},"year:1987":{"rank":25,"total":188}},"score":11.856000000000002,"debutScore":0.17,"peakScore":0.787,"duration":6,"genres":[{"instanceSlug":"pop","title":"Pop","parents":[]}],"playlists":[],"source":{},"debutEra":{"slug":"1987-02","title":"February 1987","type":"month","decade":1980,"year":1987,"month":2},"rank":334}