{"title":"Xanadu","instanceSlug":998,"tags":[],"parents":[],"genre":"orchestral-rock","debut":"1980-09","source":"xanadu","playlists":[],"ranks":[15.9,9.2,5.3,4.6,6.1,8.09,10.73,14.22,18.86,25.01,33.17,43.99,58.33,77.35,102.58,136.03],"artists":[{"slug":"olivia-newton-john","title":"Olivia Newton-John","roleSlug":true},{"slug":"electric-light-orchestra","title":"Electric Light Orchestra","roleSlug":true}],"debutRank":15.9,"peakRank":4.6,"duration":4,"score":6.96,"genres":[{"slug":"orchestral-rock","title":"Orchestral Rock"}],"rank":1051}