{"title":"Liberian Girl","instanceSlug":"libgirl","tags":[],"genre":"pop","debut":1983,"source":{"title":"Thriller","instanceSlug":"thriller","tags":["michael-jackson"],"type":"album"},"playlists":[],"artists":[{"slug":"michael-jackson","title":"Michael Jackson","roleSlug":true},{"slug":"quincy-jones","title":"Quincy Jones","roleSlug":"producer"}],"scores":[0.1,0.2,0.3,0.4,0.45,0.42,0.415,0.405,0.39,0.37,0.345,0.315,0.28,0.24,0.195,0.145,0.09,0.03,0],"ranks":{"artist:michael-jackson":{"rank":41,"total":57},"artist:quincy-jones":{"rank":11,"total":13},"genre:pop":{"rank":528,"total":1382},"source:thriller":{"rank":8,"total":9},"decade:1980s":{"rank":595,"total":1496},"year:1983":{"rank":73,"total":149}},"score":5.090000000000001,"debutScore":0.1,"peakScore":0.45,"duration":5,"genres":[{"instanceSlug":"pop","title":"Pop","parents":[]}],"debutEra":{"slug":1983,"title":1983,"type":"year","decade":1980,"year":1983},"rank":1090}