{"title":"Brandy","instanceSlug":"brandy","tags":["1990s","2000s"],"parents":[],"genres":[],"members":[],"origin":"","birth":"","death":"","complete":true,"songs":[{"title":"Sittin' Up In My Room","instanceSlug":1897,"tags":[],"parents":[],"genre":"soul","debut":"1996-01","playlists":[],"ranks":[14,4.2,2.2,1.9,1.85,1.97,2.25,2.81,3.52,4.39,5.49,6.87,8.58,10.73,13.41,16.76,20.95,26.19,32.74,40.93,51.16,63.95,79.94,99.92],"artists":[{"slug":"brandy","title":"Brandy","roleSlug":true}],"debutRank":14,"peakRank":1.85,"duration":6,"score":23.05,"genres":[{"slug":"soul","title":"Soul"}],"rank":1}],"score":23.05,"songAdjustedAverage":23.05}