{"title":"Crowded House","instanceSlug":"crowded-house","tags":[],"parents":[],"genres":["rock"],"members":[],"complete":true,"origin":"melbourne","birth":"","death":"","type":"g","songs":[{"title":"Something So Strong","instanceSlug":976,"tags":[],"parents":[],"genre":"pop","debut":"1987-06","playlists":[],"ranks":[17.9,10.7,8,7.3,7.7,9,11.25,14.06,17.58,21.97,27.47,34.33,42.92,53.64,67.06,83.82],"artists":[{"slug":"crowded-house","title":"Crowded House","roleSlug":true}],"debutRank":17.9,"peakRank":7.3,"duration":4,"score":5.51,"genres":[{"slug":"pop","title":"Pop"}],"rank":1},{"title":"Don't Dream It's Over","instanceSlug":843,"tags":[],"parents":[],"genre":"pop","debut":"1987-03","playlists":[],"ranks":[15.9,9.4,6.2,8.3,11.11,14.87,19.91,26.66,35.69,47.77,63.96,85.62],"artists":[{"slug":"crowded-house","title":"Crowded House","roleSlug":true}],"debutRank":15.9,"peakRank":6.2,"duration":3,"score":3.95,"genres":[{"slug":"pop","title":"Pop"}],"rank":2}],"score":9.46,"songAdjustedAverage":6.69}