{"title":"Frank Stallone","instanceSlug":"frank-stallone","tags":[],"parents":[],"genres":[],"members":[],"complete":false,"origin":"us","birth":"","death":"","type":"m","songs":[{"title":"Far from Over","instanceSlug":739,"tags":[],"parents":[],"genre":"pop","debut":"1983-09","source":"staying-alive","playlists":[],"ranks":[15.2,6,3,2.8,3.12,3.59,4.13,4.75,5.46,6.28,7.22,8.3,9.54,10.98,12.62,14.52,16.69,19.2,22.08,25.39,29.2,33.58,38.61,44.4,51.06,58.72,67.53,77.66],"artists":[{"slug":"frank-stallone","title":"Frank Stallone","roleSlug":true}],"debutRank":15.2,"peakRank":2.8,"duration":7,"score":18.71,"genres":[{"slug":"pop","title":"Pop"}],"rank":1}],"score":18.71,"songAdjustedAverage":18.71,"rank":270}