{"title":"Frida","instanceSlug":"frida","tags":[],"parents":[],"genres":[],"members":[],"complete":false,"origin":"","birth":"","death":"","type":{"title":"Solo Female","artists":[],"slug":"f"},"songs":[{"title":"I Know There's Something Going On","instanceSlug":70,"tags":[],"playlists":[{"slug":"feb13","title":"Feb. 13: Breakups, Cheating & Lost Loves"},{"slug":"cheating","title":"Songs about Cheating"}],"genre":"pop","debut":"1983-02","ranks":[13.9,7.9,4.5,3.2,3.5,4.2,5.04,7.06,11.29,20.32,40.64,89.41],"artists":[{"slug":"frida","title":"Frida","roleSlug":true}],"debutRank":13.9,"peakRank":3.2,"duration":3,"score":10.95,"genres":[{"slug":"pop","title":"Pop"}],"source":null,"rank":1}],"score":10.95,"songAdjustedAverage":10.95,"rank":404}