{"title":"OXO","instanceSlug":"oxo","tags":[],"parents":[],"genres":[],"members":[],"xref":[],"complete":false,"origin":"","birth":"","death":"","type":"g","songs":[{"title":"Whirly Girl","instanceSlug":1613,"tags":["girl"],"parents":[],"genre":"dance","debut":"1983-04","playlists":[],"ranks":[9,1.5,1.08,1.12,1.23,1.47,1.84,2.3,2.87,3.59,4.49,5.61,7.01,8.76,10.95,13.69,17.11,21.39,26.74,33.42,41.78,52.22,65.28,81.6],"artists":[{"slug":"oxo","title":"OXO","roleSlug":true}],"debutRank":9,"peakRank":1.08,"duration":6,"score":28.65,"genres":[{"slug":"dance","title":"Dance"}],"rank":1}],"score":28.65,"songAdjustedAverage":28.65,"rank":49}