{"title":"Run-DMC","instanceSlug":"run-dmc","tags":[],"parents":[],"genres":[],"members":[],"xref":[],"complete":false,"origin":"","birth":"","death":"","type":"g","songs":[{"title":"Walk This Way","instanceSlug":116,"tags":["this","walk","way"],"parents":[],"genre":"rap","debut":"1986-08","ranks":[19,14,10,8,7.5,7.7,9,11.25,14.06,17.58,21.97,27.47,34.33,42.92,53.64,67.06],"artists":[{"slug":"run-dmc","title":"Run-DMC","roleSlug":true}],"debutRank":19,"peakRank":7.5,"duration":4,"score":5.85,"genres":[{"slug":"rap","title":"Rap"}],"playlists":[],"rank":1}],"score":5.85,"songAdjustedAverage":5.85,"rank":636}