[{"type":"artist","route":"artist/living-in-a-box","title":"Living in a Box","score":21.87,"songCount":1,"artistCount":0},{"type":"artist","route":"artist/living-colour","title":"Living Colour","score":11.66,"songCount":1,"artistCount":0},{"type":"geo","route":"geo/liverpool","title":"Liverpool","score":210.15,"songCount":0,"artistCount":6},{"type":"source","route":"source/live-and-let-die","title":"Live and Let Die","score":0,"songCount":1,"artistCount":0},{"type":"song","route":"song/1747","title":"Living in America","score":27.46,"songCount":0,"artistCount":1},{"type":"song","route":"song/1336","title":"I Live By the Groove","score":26.96,"songCount":0,"artistCount":1},{"type":"song","route":"song/1027","title":"Living on a Prayer","score":26.11,"songCount":0,"artistCount":1},{"type":"song","route":"song/1041","title":"Living La Vida Loca","score":26.03,"songCount":0,"artistCount":1},{"type":"song","route":"song/317","title":"Living in a Box","score":21.87,"songCount":0,"artistCount":1},{"type":"song","route":"song/961","title":"One of the Living","score":18.87,"songCount":0,"artistCount":1},{"type":"song","route":"song/1244","title":"Living in Danger","score":18.14,"songCount":0,"artistCount":1},{"type":"song","route":"song/1067","title":"Live and Learn","score":16.23,"songCount":0,"artistCount":1},{"type":"song","route":"song/2525","title":"Time of Our Lives","score":14.74,"songCount":0,"artistCount":2},{"type":"song","route":"song/2082","title":"Livin' On The Edge","score":13.54,"songCount":0,"artistCount":1},{"type":"song","route":"song/1453","title":"I Live For Your Love","score":9.95,"songCount":0,"artistCount":1},{"type":"song","route":"song/1923","title":"The Living Years","score":9.37,"songCount":0,"artistCount":2},{"type":"song","route":"song/462","title":"I Don't Want to Live Without You","score":8.61,"songCount":0,"artistCount":1},{"type":"song","route":"song/1035","title":"Live & Die","score":8.19,"songCount":0,"artistCount":1},{"type":"song","route":"song/851","title":"Live to Tell","score":6.57,"songCount":0,"artistCount":1},{"type":"song","route":"song/2301","title":"How Am I Supposed To Live Without You","score":0.86,"songCount":0,"artistCount":1},{"type":"song","route":"song/2608","title":"Tryin' to Live My Life Without You","score":0,"songCount":0,"artistCount":1},{"type":"song","route":"song/2633","title":"Livin' for the Weekend","score":0,"songCount":0,"artistCount":1},{"type":"song","route":"song/2925","title":"Living Inside Myself","score":0,"songCount":0,"artistCount":1},{"type":"song","route":"song/1793","title":"Living in a Fantasy","score":0,"songCount":0,"artistCount":1},{"type":"song","route":"song/1374","title":"To Live and Die in LA","score":0,"songCount":0,"artistCount":1},{"type":"song","route":"song/2002","title":"I Don't Wanna Live Without Your Love","score":0,"songCount":0,"artistCount":1},{"type":"song","route":"song/1482","title":"Forever Live and Die","score":0,"songCount":0,"artistCount":1},{"type":"song","route":"song/2140","title":"Living For the City","score":0,"songCount":0,"artistCount":1},{"type":"song","route":"song/1519","title":"I Live For Loving You","score":0,"songCount":0,"artistCount":1},{"type":"song","route":"song/2228","title":"Live & Let Die","score":0,"songCount":0,"artistCount":1},{"type":"song","route":"song/2274","title":"Livin' Thing","score":0,"songCount":0,"artistCount":1},{"type":"song","route":"song/2302","title":"How Am I Supposed To Live Without You","score":0,"songCount":0,"artistCount":1},{"type":"song","route":"song/liveletdie1","title":"Live and Let Die","score":0,"songCount":0,"artistCount":1},{"type":"song","route":"song/liveletdie2","title":"Live and Let Die","score":0,"songCount":0,"artistCount":1}]